{"cameraMode":{"drawMode":0,"name":"Shaded","section":"Shading Mode"},"sceneLighting":true,"audioPlay":false,"sceneViewState":{"showFog":true,"showMaterialUpdate":false,"showSkybox":true,"showFlares":true,"showImageEffects":true,"showParticleSystems":true,"showVisualEffectGraphs":true,"m_FxEnabled":true},"in2DMode":false,"pivot":{"x":-221.35635375976563,"y":0.4052976369857788,"z":240.83798217773438},"rotation":{"x":-0.20999325811862946,"y":-0.7145958542823792,"z":0.24117903411388398,"w":-0.6221983432769775},"size":30.72110366821289,"orthographic":false}